{
  "Jobs": [
    {
      "orchestra": "The Cleveland Orchestra",
      "position": "Principal Trombone",
      "link": "https://www.clevelandorchestra.com/contact/auditions-careers/musician-auditions/",
      "country": "USA",
      "closingDate": "May 3, 2021",
      "auditionDate": "October 18, 2021",
      "excerpts": [
        "Berg - Three Pieces for Orchestra",
        "berliozFaust",
        "brahms1",
        "brahms2",
        "brahms4",
        "bruckner7",
        "Hindemith - Symphonic Metamorphosis",
        "mahler3",
        "mozartRequiem",
        "ravelBolero",
        "Ravel - L’enfant et les Sortileges",
        "rossiniWilliamTell",
        "schumann3",
        "schumann4",
        "straussZarathustra",
        "straussHeldenleben",
        "straussEulenspiegel",
        "Stravinsky - Pulcinella",
        "wagnerLohengrin",
        "wagnerTannhauser",
        "wagnerValkyrie",
        "saintSaens3",
        "tchaikovsky6"
      ]
    },
    {
      "orchestra": "The Cleveland Orchestra",
      "position": "Bass Trombone",
      "link": "https://www.clevelandorchestra.com/contact/auditions-careers/musician-auditions/",
      "country": "USA",
      "closingDate": "May 3, 2021",
      "auditionDate": "October 25, 2021",
      "excerpts": [
        "Bartók - Concerto for Orchestra",
        "Bartók - Miraculous Mandarin",
        "beethoven9",
        "berliozFaust",
        "Berg - Violin Concerto",
        "brahms1",
        "brahms2",
        "brahms4",
        "franckD",
        "haydnCreation",
        "Kodaly - Háry János",
        "Mahler - Symphony No. 6",
        "mahler7",
        "Mendelssohn - Symphony No. 5",
        "Prokofiev - Symphony No. 5",
        "respighiFountains",
        "Respighi - Pines of Rome",
        "rossiniWilliamTell",
        "schubert9",
        "schumann3",
        "straussZarathustra",
        "straussHeldenleben",
        "straussEulenspiegel",
        "tchaikovsky6",
        "wagnerLohengrin",
        "wagnerTannhauser",
        "wagnerValkyrie",
        "wagnerRheingold"
      ]
    },
    {
      "orchestra": "ICO Magna Grecia Orchestra",
      "position": "Principal Trombone with obl. of tutti",
      "link": "https://www.orchestramagnagrecia.info/vuoi-suonare-con-noi",
      "country": "Italy",
      "closingDate": "May 31, 2021",
      "auditionDate": "",
      "excerpts": [
        "Bernstein - Symphonic Dances from West Side Story",
        "brahms1",
        "Gershwin - An American in Paris",
        "ravelBolero",
        "rossiniWilliamTell",
        "mahler3",
        "Stravinsky - Pulcinella",
        "wagnerTannhauser"
      ]
    },
    {
      "orchestra": "Slovene National Theater",
      "position": "1. Trombone",
      "link": "https://www.sng-mb.si/",
      "country": "Slovenia",
      "closingDate": "June 13, 2021",
      "auditionDate": "July 5, 2021",
      "excerpts": []
    },
    {
      "orchestra": "United States Air Force Band of the Golden West",
      "position": "Trombone",
      "link": "https://www.music.af.mil/Auditions/Upcoming-Vacancies/",
      "country": "USA",
      "closingDate": "June 20, 2021",
      "auditionDate": "August 6, 2021",
      "excerpts": []
    },
    {
      "orchestra": "Tokyo Metropolitan Symphony Orchestra",
      "position": "2nd Trombone",
      "link": "https://tmso.or.jp/e/tmso/audition/audition_tb210709/",
      "country": "Japan",
      "closingDate": "July 9, 2021",
      "auditionDate": "September 28, 2021",
      "excerpts": ["rossiniWilliamTell", "wagnerValkyrie", "mozartRequiem"]
    },
    {
      "orchestra": "Austin Symphony Orchestra",
      "position": "Principal Trombone",
      "link": "https://austinsymphony.org/about/orchestra-auditions/",
      "country": "USA",
      "closingDate": "August 1, 2021",
      "auditionDate": "August 25, 2021",
      "excerpts": [
        "berliozFaust",
        "brahms1",
        "brahms2",
        "mahler3",
        "mozartRequiem",
        "ravelBolero",
        "rossiniLaGazza",
        "rossiniWilliamTell",
        "schumann3",
        "straussEulenspiegel",
        "Stravinsky - Pulcinella",
        "wagnerValkyrie",
        "wagnerTannhauser"
      ]
    },
    {
      "orchestra": "Richardson Symphony Orchestra",
      "position": "Principal Trombone",
      "link": "https://richardsonsymphony.org/auditions/",
      "country": "USA",
      "closingDate": "August 1, 2021",
      "auditionDate": "August 28, 2021",
      "excerpts": [
        "berliozFaust",
        "mozartRequiem",
        "ravelBolero",
        "rossiniLaGazza",
        "wagnerValkyrie"
      ]
    },
    {
      "orchestra": "Vanemuine Theater",
      "position": "TROMBONE GROUP 3rd PLAYER",
      "link": "https://www.vanemuine.ee/en/inimesed/vacant-positions/",
      "country": "Estonia",
      "closingDate": "August 1, 2021",
      "auditionDate": "August 30, 2021",
      "excerpts": []
    },
    {
      "orchestra": "Bozeman Symphony",
      "position": "Bass Trombone",
      "link": "https://www.bozemansymphony.org/auditions.html",
      "country": "USA",
      "closingDate": "August 11, 2021",
      "auditionDate": "August 21, 2021",
      "excerpts": [
        "beethoven9",
        "berliozFaust",
        "brahms2",
        "respighiFountains",
        "wagnerRheingold"
      ]
    },
    {
      "orchestra": "United States Air Force Academy Band",
      "position": "Classical/Jazz Bass Trombone",
      "link": "https://www.music.af.mil/Auditions/Upcoming-Vacancies/",
      "country": "USA",
      "closingDate": "August 16, 2021",
      "auditionDate": "October 4, 2021",
      "excerpts": [
        "wagnerValkyrie",
        "wagnerTannhauser",
        "Fillmore - Rolling Thunder"
      ]
    },
    {
      "orchestra": "Gewandhausorchester",
      "position": "Solo-Bassposaune 100% (1) – Permanent",
      "link": "https://www.muvac.com/en/vac/gewandhausorchester-0090436",
      "country": "Germany",
      "closingDate": "August 25, 2021",
      "auditionDate": "October 12, 2021",
      "excerpts": [
        "brahms1",
        "haydnCreation",
        "schumann3",
        "rossiniWilliamTell",
        "straussHeldenleben",
        "straussEulenspiegel",
        "wagnerLohengrin",
        "wagnerValkyrie",
        "Wagner - Die Meistersinger von Nürnberg",
        "wagnerTannhauser",
        "franckD",
        "Leoncavallo - Bajazzo",
        "Strauss - Rosenkavalier",
        "wagnerRheingold",
        "Strauss - Elektra",
        "Strauss - Die Frau ohne Schatten"
      ]
    },
    {
      "orchestra": "Kuopio Symphony Orchestra",
      "position": "Principal Trombone",
      "link": "https://www.kuopio.fi/kuntarekry",
      "country": "Finland",
      "closingDate": "September 1, 2021",
      "auditionDate": "October 1, 2021",
      "excerpts": []
    },
    {
      "orchestra": "Noord Nederlands Orkest",
      "position": "2nd Trombone",
      "link": "https://nno.nu/nno-en/jobs-en/2nd-trombone-90-3",
      "country": "Netherlands",
      "closingDate": "September 6, 2021",
      "auditionDate": "October 25, 2021",
      "excerpts": []
    },
    {
      "orchestra": "Orchestre Philharmonique de Radio France",
      "position": "Second trombone, playing third trombone, playing bass trombone",
      "link": "https://www.maisondelaradio.fr/page/concours-de-recrutement-recrutement-auditions",
      "country": "France",
      "closingDate": "September 8, 2021",
      "auditionDate": "",
      "excerpts": [
        "mozartRequiem",
        "rossiniLaGazza",
        "straussHeldenleben",
        "rimskyKorsakovRussianEaster",
        "haydnCreation",
        "berliozFaust",
        "schumann3",
        "Bartók - Miraculous Mandarin",
        "rimskyKorsakovScheherazade",
        "straussEulenspiegel",
        "mahler5",
        "Berg - Three Pieces for Orchestra",
        "mahler2",
        "straussZarathustra",
        "rossiniWilliamTell",
        "straussAlpine",
        "Mahler - Symphony No. 6",
        "stravinskyFirebird",
        "saintSaens3",
        "beethoven9",
        "straussBorgeois",
        "wagnerRheingold",
        "bruckner7",
        "wagnerValkyrie",
        "wagnerLohengrin",
        "Berg - Wozzeck"
      ]
    },
    {
      "orchestra": "State Opera - Rousse",
      "position": "Tenor Trombone",
      "link": "https://ruseopera.com/",
      "country": "Bulgaria",
      "closingDate": "September 10, 2021",
      "auditionDate": "September 11, 2021",
      "excerpts": [
        "mozartRequiem",
        "ravelBolero",
        "rossiniLaGazza",
        "rossiniWilliamTell"
      ]
    },
    {
      "orchestra": "State Opera - Rousse",
      "position": "Bass Trombone",
      "link": "https://ruseopera.com/",
      "country": "Bulgaria",
      "closingDate": "September 10, 2021",
      "auditionDate": "September 11, 2021",
      "excerpts": [
        "bachCelloSuite",
        "berliozFaust",
        "wagnerValkyrie",
        "rossiniWilliamTell",
        "Kodaly - Háry János"
      ]
    },
    {
      "orchestra": "Boise Philharmonic Orchestra",
      "position": "Trombone II",
      "link": "https://boisephil.org/about/auditions/",
      "country": "USA",
      "closingDate": "September 10, 2021",
      "auditionDate": "September 24, 2021",
      "excerpts": [
        "berliozFaust",
        "holstPlanets",
        "mahler5",
        "mozartRequiem",
        "ravelBolero",
        "rimskyKorsakovRussianEaster",
        "rossiniWilliamTell",
        "rossiniLaGazza",
        "straussHeldenleben",
        "wagnerValkyrie"
      ]
    },
    {
      "orchestra": "The Norwegian National Opera & Ballet",
      "position": "Basstrombone",
      "link": "https://operaen.no/en/about-us-oslo-operahouse/Vacancies/",
      "country": "Norway",
      "closingDate": "September 10, 2021",
      "auditionDate": "October 25, 2021",
      "excerpts": ["wagnerRheingold", "haydnCreation", "respighiFountains"]
    },
    {
      "orchestra": "Euskadiko Orkestra - Basque National Orchestra",
      "position": "Trombón Tutti (1)",
      "link": "https://www.muvac.com/en/vac/euskadiko-orkestra-basque-national-orchestra-8460682",
      "country": "Spain",
      "closingDate": "September 17, 2021",
      "auditionDate": "October 14, 2021",
      "excerpts": [
        "mozartRequiem",
        "straussZarathustra",
        "straussHeldenleben",
        "rimskyKorsakovScheherazade",
        "rossiniWilliamTell",
        "schumann3",
        "berliozFaust",
        "wagnerValkyrie",
        "straussEulenspiegel",
        "bruckner7",
        "brahms4",
        "schumann4",
        "Mahler - Symphony No. 9"
      ]
    },
    {
      "orchestra": "Polizeiorchester Niedersachsen",
      "position": "1. Posaune",
      "link": "https://www.zpd.polizei-nds.de/startseite/zpd_als_arbeitgeber/stellenangebote/musikerin-oder-musiker-m-w-d-fur-1-posaune-115673.html",
      "country": "Germany",
      "closingDate": "September 30, 2021",
      "auditionDate": "",
      "excerpts": []
    },
    {
      "orchestra": "Portland Symphony Orchestra",
      "position": "Bass Trombone",
      "link": "https://portlandsymphony.org/about-pso/musicians/auditions-and-employment/#PC",
      "country": "USA",
      "closingDate": "October 4, 2021",
      "auditionDate": "October 19, 2021",
      "excerpts": [
        "bachCelloSuite",
        "beethoven9",
        "berliozFaust",
        "franckD",
        "haydnCreation",
        "Kodaly - Háry János",
        "respighiFountains",
        "rossiniWilliamTell",
        "schumann3",
        "straussHeldenleben",
        "wagnerRheingold",
        "wagnerValkyrie"
      ]
    },
    {
      "orchestra": "San Francisco Symphony",
      "position": "Principal Trombone",
      "link": "https://www.sfsymphony.org/About-SFS/Auditions/Orchestra-Auditions",
      "country": "USA",
      "closingDate": "October 7, 2021",
      "auditionDate": "January 24, 2022 ",
      "excerpts": []
    },
    {
      "orchestra": "Oklahoma City Philharmonic",
      "position": "Principal Trombone",
      "link": "https://www.okcphil.org/principal-trombone/",
      "country": "USA",
      "closingDate": "October 15, 2021",
      "auditionDate": "October 26, 2021",
      "excerpts": [
        "berliozFaust",
        "berliozSymphonie",
        "mahler3",
        "ravelBolero",
        "rossiniWilliamTell",
        "saintSaens3",
        "schumann3",
        "straussZarathustra",
        "straussEulenspiegel",
        "wagnerValkyrie",
        "wagnerTannhauser",
        "brahms2",
        "bruckner8",
        "Hindemith - Symphonic Metamorphosis",
        "verdiNabucco"
      ]
    },
    {
      "orchestra": "Welsh National Opera",
      "position": "Sub-Principal Trombone (playing Section Principal as required)",
      "link": "https://wno.org.uk/vacancy/sub-principal-trombone-playing-section-principal-as-required",
      "country": "United Kingdom",
      "closingDate": "October 15, 2021",
      "auditionDate": "",
      "excerpts": [
        "bachCelloSuite",
        "mozartRequiem",
        "wagnerValkyrie",
        "Mozart - The Magic Flute",
        "ravelBolero",
        "wagnerLohengrin",
        "Mascagni - Cavalleria rusticana",
        "Leoncavallo - Pagliacci",
        "mahler5",
        "mahler2",
        "rossiniLaGazza",
        "Berg - Wozzeck",
        "Berg - Lulu",
        "Verdi - Il Trovatore",
        "Verdi - Otello"
      ]
    },
    {
      "orchestra": "Orchestre Philharmonique de Nice",
      "position": "Un trombone solo",
      "link": "www.opera-nice.org",
      "country": "France",
      "closingDate": "October 18, 2021",
      "auditionDate": "November 15, 2021",
      "excerpts": []
    },
    {
      "orchestra": "Teatro Regio di Torino",
      "position": "Secondo Trombone e seguenti",
      "link": "https://www.teatroregio.torino.it/selezione-personale#orchestra",
      "country": "Italy",
      "closingDate": "October 23, 2021",
      "auditionDate": "",
      "excerpts": [
        "mozartRequiem",
        "rossiniWilliamTell",
        "wagnerValkyrie",
        "berliozFaust",
        "Respighi - Pines of Rome",
        "wagnerLohengrin",
        "Verdi - I vespri siciliani",
        "straussZarathustra",
        "wagnerTannhauser",
        "Verdi - Otello",
        "rossiniLaGazza",
        "mahler3"
      ]
    },
    {
      "orchestra": "Baltic Sea Philharmonic",
      "position": "Trombone",
      "link": "https://baltic-sea-philharmonic.eu/digitaltalenttour/",
      "country": "Germany",
      "closingDate": "October 31, 2021",
      "auditionDate": "December 6, 2021",
      "excerpts": ["Tchaikovsky - Sleeping Beauty: A Dramatic Symphony"]
    },
    {
      "orchestra": "Opera North",
      "position": "Principal 2nd Trombone",
      "link": "https://www.operanorth.co.uk/about-us/jobs/",
      "country": "United Kingdom",
      "closingDate": "November 1, 2021",
      "auditionDate": "November 22, 2021",
      "excerpts": []
    },
    {
      "orchestra": "Tasmanian Symphony Orchestra",
      "position": "Tutti Trombone",
      "link": "https://www.tso.com.au/wp-content/uploads/2021/08/TSO-Website-Advert-Tutti-trombone.pdf",
      "country": "Australia",
      "closingDate": "November 2, 2021",
      "auditionDate": "November 16, 2021",
      "excerpts": []
    },
    {
      "orchestra": "Jacksonville Symphony",
      "position": "Principal Trombone",
      "link": "https://www.jaxsymphony.org/about/employment-auditions/",
      "country": "USA",
      "closingDate": "November 8, 2021",
      "auditionDate": "November 8, 2021",
      "excerpts": []
    },
    {
      "orchestra": "Teatro Massimo",
      "position": "Primo trombone con obbligo della fila e del trombone contralto",
      "link": "https://www.teatromassimo.it/audizioni-selezioni-e-bandi/audizioni-e-selezioni-976/audizione-per-professori-d-orchestra-stagione-2022.html",
      "country": "Italy",
      "closingDate": "November 15, 2021",
      "auditionDate": "November 22, 2021",
      "excerpts": []
    },
    {
      "orchestra": "Slovak National Theatre",
      "position": "3rd player in trombones section , bass trombone",
      "link": "https://snd.sk/konkurzy-na-umelcov",
      "country": "Slovakia",
      "closingDate": "November 20, 2021",
      "auditionDate": "November 30, 2021",
      "excerpts": [
        "Dvořák - Rusalka",
        "Frešo - Narodil sa chrobáčik",
        "Leoncavallo - Pagliacci",
        "Mascagni - Cavalleria rusticana",
        "Massenet - Werther",
        "Prokofiev - Romeo and Juliet",
        "Puccini - La bohème",
        "rossiniWilliamTell",
        "rossiniLaGazza",
        "Suchoň: Krútňava",
        "Tchaikovsky - Nutcracker",
        "Tchaikivsky - Swan Lake",
        "Verdi - Aida",
        "Verdi - Don Carlo",
        "Verdi - Falstaff",
        "Verdi - Macbeth",
        "Verdi - Otello",
        "Verdi - Requiem",
        "wagnerValkyrie"
      ]
    },
    {
      "orchestra": "Orchestre Symphonique de Mulhouse",
      "position": "3e Trombone, jouant Trombone basse, 2e Trombone et Trombone",
      "link": "www.orchestre-mulhouse.fr",
      "country": "France",
      "closingDate": "November 25, 2021",
      "auditionDate": "December 9, 2021",
      "excerpts": [
        "rossiniLaGazza",
        "beethoven9",
        "Delibes - Coppélia",
        "haydnCreation",
        "schumann3",
        "rossiniWilliamTell",
        "wagnerLohengrin",
        "straussEulenspiegel"
      ]
    },
    {
      "orchestra": "Opéra National de Paris",
      "position": "Trombone basse solo jouant le 3ème trombone – 1 poste",
      "link": "https://www.operadeparis.fr/artistes/concours-et-auditions/orchestre",
      "country": "France",
      "closingDate": "November 30, 2021",
      "auditionDate": "December 14, 2021",
      "excerpts": []
    },
    {
      "orchestra": "Guiyang Symphony Orchestra",
      "position": "Trombone, principal",
      "link": "https://www.gyso.cn/Pages/Show_List.aspx?menu_id=108&isEn=1",
      "country": "China",
      "closingDate": "November 30, 2021",
      "auditionDate": "November 30, 2021",
      "excerpts": ["straussEulenspiegel", "mozartRequiem", "mahler3"]
    },
    {
      "orchestra": "Opéra de Marseille",
      "position": "DEUXIÈME TROMBONE JOUANT LE TROISIÈME",
      "link": "opera.marseille.fr",
      "country": "France",
      "closingDate": "January 11, 2022",
      "auditionDate": "January 21, 2022",
      "excerpts": []
    }
  ]
}
